odoo/addons/account_invoice_margin/README.rst
odoo/addons/account_invoice_margin/__init__.py
odoo/addons/account_invoice_margin/__manifest__.py
odoo/addons/account_invoice_margin/hooks.py
odoo/addons/account_invoice_margin/i18n/account_invoice_margin.pot
odoo/addons/account_invoice_margin/i18n/es.po
odoo/addons/account_invoice_margin/i18n/fr.po
odoo/addons/account_invoice_margin/i18n/fr_FR.po
odoo/addons/account_invoice_margin/i18n/it.po
odoo/addons/account_invoice_margin/models/__init__.py
odoo/addons/account_invoice_margin/models/account_invoice.py
odoo/addons/account_invoice_margin/readme/CONTRIBUTORS.md
odoo/addons/account_invoice_margin/readme/DESCRIPTION.md
odoo/addons/account_invoice_margin/readme/USAGE.md
odoo/addons/account_invoice_margin/report/__init__.py
odoo/addons/account_invoice_margin/report/account_invoice_report.py
odoo/addons/account_invoice_margin/security/account_invoice_margin_security.xml
odoo/addons/account_invoice_margin/static/description/account_invoice_form.png
odoo/addons/account_invoice_margin/static/description/account_invoice_tree.png
odoo/addons/account_invoice_margin/static/description/icon.png
odoo/addons/account_invoice_margin/static/description/index.html
odoo/addons/account_invoice_margin/tests/__init__.py
odoo/addons/account_invoice_margin/tests/test_account_invoice_margin.py
odoo/addons/account_invoice_margin/views/account_invoice_margin_view.xml
odoo_addon_account_invoice_margin-18.0.1.0.0.2.dist-info/METADATA
odoo_addon_account_invoice_margin-18.0.1.0.0.2.dist-info/WHEEL
odoo_addon_account_invoice_margin-18.0.1.0.0.2.dist-info/top_level.txt
odoo_addon_account_invoice_margin-18.0.1.0.0.2.dist-info/RECORD
